ProgressBarPy/__init__.py
ProgressBarPy/exceptions.py
ProgressBarPy/progressbar.py
ProgressBarPy-0.0.6.dist-info/METADATA
ProgressBarPy-0.0.6.dist-info/WHEEL
ProgressBarPy-0.0.6.dist-info/top_level.txt
ProgressBarPy-0.0.6.dist-info/RECORD
