Metadata-Version: 2.1
Name: ProgressBarPy
Version: 0.0.6
Summary: This package adds simple windowed progressbar.
Home-page: https://github.com/Vladislavus1/ProgressBarPy
Author: Vladislavus1
